venture/__init__.py
venture/browse.py
venture/cli.py
venture/config.py
venture/ext.py
venture/icons.py
venture/pango.py
venture/py.typed
venture/quicklaunch.py
venture/util.py
venture-3.1.0.dist-info/METADATA
venture-3.1.0.dist-info/WHEEL
venture-3.1.0.dist-info/entry_points.txt
venture-3.1.0.dist-info/RECORD
