Metadata-Version: 2.1
Name: venture
Version: 3.1.0
Summary: Rofi / Wofi based project selector
Home-page: https://github.com/seanrcollings/venture
License: MIT
Author: Sean Collings
Author-email: seanrcollings@gmail.com
Requires-Python: >=3.10,<4.0
Classifier: License :: OSI Approved :: MIT License
Classifier: Programming Language :: Python :: 3
Classifier: Programming Language :: Python :: 3.10
Classifier: Programming Language :: Python :: 3.11
Requires-Dist: arc-cli (>=8.0.0,<9.0.0)
Requires-Dist: pydantic (>=1.8.2,<2.0.0)
Requires-Dist: toml (>=0.10.2,<0.11.0)
Requires-Dist: ujson (>=4.0.2,<5.0.0)
Requires-Dist: xdg (>=5.1.1,<6.0.0)
